<?xml version="1.0" encoding="utf-8"?>
<actor version="1">
  <castshadow/>
  <group>
    <variant frequency="1" name="Radar crewmen">
      <mesh>structures/SHA/rep_worker.dae</mesh>
      <props>
        <prop actor="particle/plasma.xml" attachpoint="root"/>
      </props>
      <textures>
        <texture file="structural/reptilian_struct.png" name="baseTex"/>
        <texture file="structural/space_spec.png" name="specTex"/>
        <texture file="structural/space_norm.png" name="normTex"/>
      </textures>
    </variant>
  </group>
  <material>basic_trans_parallax_spec.xml</material>
</actor>  
